imports/__init__.py
imports/cli.py
imports/imports.py
imports-0.1.4.dist-info/DESCRIPTION.rst
imports-0.1.4.dist-info/METADATA
imports-0.1.4.dist-info/RECORD
imports-0.1.4.dist-info/WHEEL
imports-0.1.4.dist-info/entry_points.txt
imports-0.1.4.dist-info/metadata.json
imports-0.1.4.dist-info/top_level.txt
