Metadata-Version: 1.1
Name: imports
Version: 0.1.4
Summary: A helper tool to identify the unused installed packages that are listed on requirements.txt
Home-page: https://github.com/joaopcanario/imports
Author: João Paulo Canário
Author-email: jopacanario@gmail.com
License: MIT license
Keywords: imports
Platform: UNKNOWN
Classifier: Development Status :: 2 - Pre-Alpha
Classifier: Intended Audience :: Developers
Classifier: License :: OSI Approved :: MIT License
Classifier: Natural Language :: English
Classifier: Programming Language :: Python :: 3
Classifier: Programming Language :: Python :: 3.4
Classifier: Programming Language :: Python :: 3.5
Classifier: Programming Language :: Python :: 3.6
